infer_client/__init__.py
infer_client/error.py
infer_client/inference.py
infer_client/adapters/__init__.py
infer_client/adapters/onnx.py
infer_client/adapters/triton.py
infer_client/adapters/tritonclient_grpc_custom.py
infer_client-0.1.0.dist-info/LICENSE.txt
infer_client-0.1.0.dist-info/METADATA
infer_client-0.1.0.dist-info/WHEEL
infer_client-0.1.0.dist-info/top_level.txt
infer_client-0.1.0.dist-info/RECORD
