Metadata-Version: 2.1
Name: infer-client
Version: 0.1.0
Summary: Abstraction for AI Inference Client
Author-email: Dao Quang Duy <duydaoquang12@gmail.com>
Maintainer-email: Rabiloo Developers <oss@rabiloo.com>
License: The MIT License
Project-URL: Homepage, https://github.com/rabiloo/python-infer-client
Project-URL: Repository, https://github.com/rabiloo/python-infer-client
Project-URL: Bug Tracker, https://github.com/rabiloo/python-infer-client/issues
Keywords: infer-client,onnxruntime,onnxruntime-gpu,tritonclient
Classifier: Programming Language :: Python :: 3
Classifier: License :: OSI Approved :: MIT License
Classifier: Operating System :: OS Independent
Classifier: Development Status :: 2 - Pre-Alpha
Requires-Python: >=3.10
License-File: LICENSE.txt
Requires-Dist: numpy
Provides-Extra: dev
Requires-Dist: black ; extra == 'dev'
Requires-Dist: flake8 ; extra == 'dev'
Requires-Dist: flake8-pyproject ; extra == 'dev'
Requires-Dist: pytest ; extra == 'dev'
Requires-Dist: typing-extensions ; extra == 'dev'
Provides-Extra: onnxruntime
Requires-Dist: onnxruntime ; extra == 'onnxruntime'
Provides-Extra: onnxruntime-gpu
Requires-Dist: onnxruntime-gpu ; extra == 'onnxruntime-gpu'
Provides-Extra: tritonclient
Requires-Dist: tritonclient[grpc] ; extra == 'tritonclient'
